setup.cfg
setup.py
andronnlib.egg-info/PKG-INFO
andronnlib.egg-info/SOURCES.txt
andronnlib.egg-info/dependency_links.txt
andronnlib.egg-info/not-zip-safe
andronnlib.egg-info/top_level.txt
dist_alx/__init__.py
dist_alx/andronnlib.py