Metadata-Version: 1.0
Name: andronnlib
Version: 160122
Summary: Andronn Library. Used in Andronn's projects.
Home-page: UNKNOWN
Author: UNKNOWN
Author-email: aljosa.juzin@gmail.com
License: UNKNOWN
Platform: UNKNOWN
